[
  {
    "full_name": "urllib3/urllib3",
    "stargazers_count": 3127,
    "open_issues_count": 110,
    "forks_count": 985
  },
  {
    "full_name": "python-pillow/Pillow",
    "stargazers_count": 10054,
    "open_issues_count": 126,
    "forks_count": 1892
  },
  {
    "full_name": "librariesio/bibliothecary",
    "stargazers_count": 77,
    "open_issues_count": 16,
    "forks_count": 39
  },
  {
    "full_name": "librariesio/bibliothecary",
    "stargazers_count": 77,
    "open_issues_count": 16,
    "forks_count": 39
  },
  {
    "full_name": "open-sauced/open-sauced",
    "stargazers_count": 751,
    "open_issues_count": 17,
    "forks_count": 357
  }
]