[
  {
    "full_name": "urllib3/urllib3",
    "stargazers_count": 3218,
    "open_issues_count": 120,
    "forks_count": 1012
  },
  {
    "full_name": "python-pillow/Pillow",
    "stargazers_count": 10392,
    "open_issues_count": 115,
    "forks_count": 1958
  },
  {
    "full_name": "librariesio/bibliothecary",
    "stargazers_count": 79,
    "open_issues_count": 16,
    "forks_count": 39
  },
  {
    "full_name": "librariesio/bibliothecary",
    "stargazers_count": 79,
    "open_issues_count": 16,
    "forks_count": 39
  },
  {
    "full_name": "open-sauced/open-sauced",
    "stargazers_count": 822,
    "open_issues_count": 9,
    "forks_count": 469
  }
]