[
  {
    "full_name": "urllib3/urllib3",
    "stargazers_count": 4027,
    "open_issues_count": 215,
    "forks_count": 1374
  },
  {
    "full_name": "python-pillow/Pillow",
    "stargazers_count": 13585,
    "open_issues_count": 130,
    "forks_count": 2446
  },
  {
    "full_name": "librariesio/bibliothecary",
    "stargazers_count": 102,
    "open_issues_count": 16,
    "forks_count": 38
  },
  {
    "full_name": "librariesio/bibliothecary",
    "stargazers_count": 102,
    "open_issues_count": 16,
    "forks_count": 38
  },
  {
    "full_name": "open-sauced/open-sauced",
    "stargazers_count": 954,
    "open_issues_count": 0,
    "forks_count": 1170
  }
]